delphi/__init__.py
delphi/core.py
delphi/types.py
delphi/utils.py
delphi-2.0.1.dist-info/DESCRIPTION.rst
delphi-2.0.1.dist-info/METADATA
delphi-2.0.1.dist-info/RECORD
delphi-2.0.1.dist-info/WHEEL
delphi-2.0.1.dist-info/dependency_links.txt
delphi-2.0.1.dist-info/metadata.json
delphi-2.0.1.dist-info/top_level.txt
