Metadata-Version: 2.0
Name: delphi
Version: 2.0.1
Summary: A framework for assembling probabilistic models from text.
Home-page: https://ml4ai.github.io/delphi/
Author: ML4AI
Author-email: adarsh@email.arizona.edu
License: UNKNOWN
Keywords: assembling models from text
Platform: UNKNOWN
Classifier: Development Status :: 3 - Alpha
Classifier: Intended Audience :: Science/Research
Classifier: Topic :: Scientific/Engineering :: Artificial Intelligence
Classifier: License :: OSI Approved :: Apache Software License
Classifier: Programming Language :: Python :: 3.6
Requires-Python: >=3.6
Provides-Extra: dev
Provides-Extra: test
Provides-Extra: docs
Requires-Dist: future
Requires-Dist: indra
Requires-Dist: matplotlib
Requires-Dist: networkx
Requires-Dist: networkx
Requires-Dist: numpy
Requires-Dist: pandas
Requires-Dist: scipy
Requires-Dist: tqdm
Provides-Extra: dev
Requires-Dist: check-manifest; extra == 'dev'
Provides-Extra: docs
Requires-Dist: sphinx-autodoc-typehints; extra == 'docs'
Requires-Dist: sphinxcontrib-bibtex; extra == 'docs'
Requires-Dist: sphinxcontrib-trio; extra == 'docs'
Provides-Extra: test
Requires-Dist: mypy; extra == 'test'
Requires-Dist: pytest; extra == 'test'
